lpython/__init__.py
lpython/lpython.py
lpython-0.0.16.0.dist-info/licenses/LICENSE
lpython-0.0.16.0.dist-info/METADATA
lpython-0.0.16.0.dist-info/WHEEL
lpython-0.0.16.0.dist-info/top_level.txt
lpython-0.0.16.0.dist-info/RECORD
