Metadata-Version: 2.4
Name: lpython
Version: 0.0.16.0
Summary: Package for adding type information to python
Home-page: https://github.com/lcompilers/lpython/
Author: Ondrej Certik
Author-email: ondrej@certik.us
Classifier: Programming Language :: Python :: 3
Classifier: License :: OSI Approved :: MIT License
Classifier: Operating System :: OS Independent
Requires-Python: >=3.6
License-File: LICENSE
Dynamic: author
Dynamic: author-email
Dynamic: classifier
Dynamic: description
Dynamic: description-content-type
Dynamic: home-page
Dynamic: license-file
Dynamic: requires-python
Dynamic: summary
